{
  "Liszt": "Classical",
  "Rossini": "Classical",
  "Percy Faith": "Jazz",
  "Schumann": "Classical",
  "Andy Williams": "Pop",
  "Mozart": "Classical",
  "Bach": "Classical",
  "Beethoven": "Classical",
  "Astrud Gilberto": "Pop",
  "Bobby Darin": "Jazz",
  "Puccini": "Classical",
  "Schubert": "Classical",
  "Cream": "Pop",
  "Prince": "Pop",
  "Maynard Ferguson": "Jazz",
  "Benny Goodman Orchestra": "Jazz",
  "Bob Dylan": "Pop",
  "Ray Charles": "Jazz",
  "Duke Ellington": "Jazz",
  "The Beatles": "Pop",
  "The Rolling Stones": "Pop",
  "Nat King Cole (Frank Sinatra)": "Jazz",
  "Talking Heads": "Pop",
  "Brook Benton": "Pop",
  "Elvis Presley": "Pop",
  "Janacek": "Classical",
  "Michael Jackson": "Pop",
  "Curtis Fuller": "Jazz",
  "Hall and Oates": "Pop"
}
